{
  "base": {
    "parent": "minecraft:builtin/entity",
    "display": {
      "firstperson_lefthand": {
        "translation": [
          0,
          -24,
          0
        ]
      },
      "firstperson_righthand": {
        "translation": [
          0,
          -24,
          0
        ]
      },
      "head": {
        "translation": [
          0,
          -21,
          0
        ]
      },
      "thirdperson_lefthand": {
        "translation": [
          0,
          -18,
          2
        ]
      },
      "thirdperson_righthand": {
        "translation": [
          0,
          -18,
          2
        ]
      }
    }
  },
  "gui_light": "front",
  "loader": "neoforge:separate_transforms",
  "perspectives": {
    "fixed": {
      "parent": "minecraft:item/generated",
      "textures": {
        "layer0": "mineraculous:item/butterfly_cane_blade"
      }
    },
    "ground": {
      "parent": "minecraft:item/generated",
      "textures": {
        "layer0": "mineraculous:item/butterfly_cane_blade"
      }
    },
    "gui": {
      "parent": "minecraft:item/generated",
      "textures": {
        "layer0": "mineraculous:item/butterfly_cane_blade"
      }
    }
  }
}